nr_merkletree
