Metadata-Version: 1.1
Name: nr-merkletree
Version: 0.1.3
Summary: Merkle Tree implementation for Python3.
Home-page: UNKNOWN
Author: Nitish Reddy Koripalli <nitish.k.reddy@gmail.com>
Author-email: UNKNOWN
License: UNKNOWN
Download-URL: https://github.com/nitred/nr-merkletree/archive/0.1.3.tar.gz
Platform: UNKNOWN
Classifier: Programming Language :: Python :: 3.5
Classifier: Programming Language :: Python :: 3.6
